{
  "Component-dbg.js": 1550503192092,
  "Component-preload.js": 1550503192124,
  "Component.js": 1550497885579,
  "controller/flower_display-dbg.controller.js": 1550503192092,
  "controller/flower_display.controller.js": 1550503068415,
  "di.code-validation.core_issues.json": 1550503191608,
  "i18n/i18n.properties": 1550495132508,
  "index.html": 1550501754569,
  "manifest-bundle.zip": 1550503192264,
  "manifest.json": 1550503191936,
  "resources.json": 1550503192186,
  "view/flower_display.view.xml": 1550497626204,
  "xs-app.json": 1550489271484
}